chrome_lens_py/__init__.py
chrome_lens_py/api.py
chrome_lens_py/constants.py
chrome_lens_py/exceptions.py
chrome_lens_py/cli/__init__.py
chrome_lens_py/cli/main.py
chrome_lens_py/core/__init__.py
chrome_lens_py/core/image_processor.py
chrome_lens_py/core/protobuf_builder.py
chrome_lens_py/core/request_handler.py
chrome_lens_py/utils/__init__.py
chrome_lens_py/utils/config_manager.py
chrome_lens_py/utils/font_manager.py
chrome_lens_py/utils/general.py
chrome_lens_py/utils/lens_betterproto.py
chrome_lens_py/utils/sharex.py
chrome_lens_py-3.3.1.dist-info/LICENSE
chrome_lens_py-3.3.1.dist-info/METADATA
chrome_lens_py-3.3.1.dist-info/WHEEL
chrome_lens_py-3.3.1.dist-info/entry_points.txt
chrome_lens_py-3.3.1.dist-info/top_level.txt
chrome_lens_py-3.3.1.dist-info/RECORD
