Metadata-Version: 2.1
Name: chrome_lens_py
Version: 3.3.1
Summary: Python library for Google Lens OCR and Translation using the crupload endpoint.
Home-page: https://github.com/bropines/chrome-lens-py
Author: Bropines
Author-email: bropines@gmail.com
License: MIT License
Classifier: Programming Language :: Python :: 3
Classifier: Programming Language :: Python :: 3.8
Classifier: Programming Language :: Python :: 3.9
Classifier: Programming Language :: Python :: 3.10
Classifier: Programming Language :: Python :: 3.11
Classifier: Programming Language :: Python :: 3.12
Classifier: Operating System :: OS Independent
Classifier: Topic :: Scientific/Engineering :: Image Recognition
Classifier: Topic :: Software Development :: Libraries :: Python Modules
Classifier: Intended Audience :: Developers
Requires-Python: >=3.8
License-File: LICENSE
Requires-Dist: httpx[socks] >=0.20
Requires-Dist: Pillow >=9.0
Requires-Dist: betterproto >=2.0.0b6
Requires-Dist: filetype >=1.0
Requires-Dist: rich >=10.0
Requires-Dist: numpy
Provides-Extra: clipboard
Requires-Dist: pyperclip >=1.8 ; extra == 'clipboard'
Provides-Extra: dev
Requires-Dist: black ; extra == 'dev'
Requires-Dist: isort ; extra == 'dev'
Requires-Dist: flake8 ; extra == 'dev'
Requires-Dist: mypy ; extra == 'dev'
Requires-Dist: pytest ; extra == 'dev'
Requires-Dist: pytest-asyncio ; extra == 'dev'
